localAugment/__init__.py
localaugment-0.2.1.dist-info/LICENSE
localaugment-0.2.1.dist-info/METADATA
localaugment-0.2.1.dist-info/WHEEL
localaugment-0.2.1.dist-info/RECORD
