Metadata-Version: 2.1
Name: localAugment
Version: 0.2.1
Summary: a package for local images augment in deep learning
Author: dream同学0
Author-email: 1399541701@qq.com
Requires-Python: >=3.11,<4.0
Classifier: Programming Language :: Python :: 3
Classifier: Programming Language :: Python :: 3.11
Classifier: Programming Language :: Python :: 3.12
Requires-Dist: matplotlib (>=3.8.3,<4.0.0)
Requires-Dist: opencv-python (>=4.9.0.80,<5.0.0.0)
Requires-Dist: pandas (>=2.2.1,<3.0.0)
